slack_cli_dashboard/__init__.py
slack_cli_dashboard/asynchronous/__init__.py
slack_cli_dashboard/asynchronous/threads.py
slack_cli_dashboard/main.py
slack_cli_dashboard/slack_data.py
slack_cli_dashboard-0.1.3.dist-info/WHEEL
slack_cli_dashboard-0.1.3.dist-info/entry_points.txt
slack_cli_dashboard-0.1.3.dist-info/METADATA
slack_cli_dashboard-0.1.3.dist-info/RECORD
